<?xml version="1.0" encoding="UTF-8"?>
	<!DOCTYPE NIR SYSTEM 'nirflessibile.dtd'>
	<NIR tipo="originale" xmlns="http://www.normeinrete.it/nir/2.2/" xmlns:dsp="http://www.normeinrete.it/nir/disposizioni/2.2/" xmlns:h="http://www.w3.org/HTML/1998/html4" xmlns:xlink="http://www.w3.org/1999/xlink">
		<LeggeRegionale>
			<meta>
				<descrittori>
					<pubblicazione norm="20061222" num="38" tipo="BURT" />
					<entratainvigore norm="20070106" />
					<redazione id="red1" nome="" norm="" />
					<urn valore="urn:nir:regione.toscana:legge:2006-12-18;62" />
					<materie vocabolario="Regione Toscana">
						<materia valore="Commercio" />
					</materie>
				</descrittori>
				<ciclodivita>
					<eventi>
						<evento data="20070106" fonte="ro1" id="t1" tipo="entrata in vigore" />
						<evento data="20071025" fonte="ra1" id="t2" tipo="modifica" />
						<evento data="20071025" fonte="ra2" id="t3" tipo="modifica" />
						<evento data="20070106" fonte="ra3" id="t4" tipo="modifica" />
						<evento data="20070106" fonte="ra4" id="t5" tipo="modifica" />
						<evento data="20070106" fonte="ra5" id="t6" tipo="modifica" />
						<evento data="20070106" fonte="ra6" id="t7" tipo="modifica" />
						<evento data="20070106" fonte="ra7" id="t8" tipo="modifica" />
						<evento data="20071025" fonte="ra8" id="t9" tipo="modifica" />
						<evento data="20071025" fonte="ra9" id="t10" tipo="modifica" />
						<evento data="20071025" fonte="ra10" id="t11" tipo="modifica" />
					</eventi>
					<relazioni>
						<originale id="ro1" xlink:href="urn:nir:regione.toscana:legge:2006-12-18;62" xlink:type="simple" />
						<attiva id="ra1" xlink:href="urn:nir:regione.toscana:legge:2004-05-31;28" xlink:type="simple" />
						<attiva id="ra2" xlink:href="urn:nir:regione.toscana:legge:2004;28" xlink:type="simple" />
						<attiva id="ra3" xlink:href="urn:nir:regione.toscana:legge:2004-05-31;28" xlink:type="simple" />
						<attiva id="ra4" xlink:href="urn:nir:regione.toscana:legge:2004-05-31;28" xlink:type="simple" />
						<attiva id="ra5" xlink:href="urn:nir:regione.toscana:legge:2004-05-31;28" xlink:type="simple" />
						<attiva id="ra6" xlink:href="urn:nir:regione.toscana:legge:2004-05-31;28" xlink:type="simple" />
						<attiva id="ra7" xlink:href="urn:nir:regione.toscana:legge:2004;28" xlink:type="simple" />
						<attiva id="ra8" xlink:href="urn:nir:regione.toscana:legge:2004-05-31;28" xlink:type="simple" />
						<attiva id="ra9" xlink:href="urn:nir:regione.toscana:legge:2004-05-31;28" xlink:type="simple" />
						<attiva id="ra10" xlink:href="urn:nir:regione.toscana:legge:2004;28" xlink:type="simple" />
					</relazioni>
				</ciclodivita>
				<disposizioni xlink:type="simple">
					<modificheattive>
						<dsp:abrogazione completa="si" implicita="no">
							<dsp:pos xlink:href="#mod1" xlink:type="simple" />
							<dsp:termine da="#t2" />
							<dsp:norma xlink:href="urn:nir:regione.toscana:legge:2004-05-31;28" xlink:type="simple">
								<dsp:pos xlink:href="urn:nir:regione.toscana:legge:2004-05-31;28#art10-com1" xlink:type="simple" />
							</dsp:norma>
							<dsp:novellando>
								<dsp:pos xlink:href="#mod1-vir1" xlink:type="simple" />
								<dsp:subarg>
									<ittig:tipo valore="parole" xmlns:ittig="http://www.ittig.cnr.it/provvedimenti/2.2" />
								</dsp:subarg>
							</dsp:novellando>
						</dsp:abrogazione>
						<dsp:integrazione completa="si" implicita="no">
							<dsp:pos xlink:href="#mod2" xlink:type="simple" />
							<dsp:termine da="#t3" />
							<dsp:norma xlink:href="urn:nir:regione.toscana:legge:2004;28" xlink:type="simple">
								<dsp:pos xlink:href="urn:nir:regione.toscana:legge:2004;28#art10-com1" xlink:type="simple" />
							</dsp:norma>
							<dsp:novella>
								<dsp:pos xlink:href="#mod2-vir1" xlink:type="simple" />
								<dsp:subarg>
									<ittig:tipo valore="comma" xmlns:ittig="http://www.ittig.cnr.it/provvedimenti/2.2" />
								</dsp:subarg>
							</dsp:novella>
						</dsp:integrazione>
						<dsp:sostituzione completa="si" implicita="no">
							<dsp:pos xlink:href="#mod3" xlink:type="simple" />
							<dsp:termine da="#t9" />
							<dsp:norma xlink:href="urn:nir:regione.toscana:legge:2004-05-31;28" xlink:type="simple">
								<dsp:pos xlink:href="urn:nir:regione.toscana:legge:2004-05-31;28#art10-com3" xlink:type="simple" />
							</dsp:norma>
							<dsp:novella>
								<dsp:pos xlink:href="#mod4-vir2" xlink:type="simple" />
								<dsp:subarg>
									<ittig:tipo valore="parole" xmlns:ittig="http://www.ittig.cnr.it/provvedimenti/2.2" />
								</dsp:subarg>
							</dsp:novella>
							<dsp:novellando>
								<dsp:pos xlink:href="#mod4-vir1" xlink:type="simple" />
								<dsp:subarg>
									<ittig:tipo valore="parole" xmlns:ittig="http://www.ittig.cnr.it/provvedimenti/2.2" />
								</dsp:subarg>
							</dsp:novellando>
						</dsp:sostituzione>
						<dsp:sostituzione completa="si" implicita="no">
							<dsp:pos xlink:href="#mod4" xlink:type="simple" />
							<dsp:termine da="#t10" />
							<dsp:norma xlink:href="urn:nir:regione.toscana:legge:2004-05-31;28" xlink:type="simple">
								<dsp:pos xlink:href="urn:nir:regione.toscana:legge:2004-05-31;28#art10-com4" xlink:type="simple" />
							</dsp:norma>
							<dsp:novella>
								<dsp:pos xlink:href="#mod4-vir2" xlink:type="simple" />
								<dsp:subarg>
									<ittig:tipo valore="parole" xmlns:ittig="http://www.ittig.cnr.it/provvedimenti/2.2" />
								</dsp:subarg>
							</dsp:novella>
							<dsp:novellando>
								<dsp:pos xlink:href="#mod4-vir1" xlink:type="simple" />
								<dsp:subarg>
									<ittig:tipo valore="parole" xmlns:ittig="http://www.ittig.cnr.it/provvedimenti/2.2" />
								</dsp:subarg>
							</dsp:novellando>
						</dsp:sostituzione>
						<dsp:integrazione completa="si" implicita="no">
							<dsp:pos xlink:href="#mod5" xlink:type="simple" />
							<dsp:termine da="#t11" />
							<dsp:norma xlink:href="urn:nir:regione.toscana:legge:2004;28" xlink:type="simple">
								<dsp:pos xlink:href="urn:nir:regione.toscana:legge:2004;28#art10-com5" xlink:type="simple" />
							</dsp:norma>
							<dsp:novella>
								<dsp:pos xlink:href="#mod5-vir1" xlink:type="simple" />
								<dsp:subarg>
									<ittig:tipo valore="comma" xmlns:ittig="http://www.ittig.cnr.it/provvedimenti/2.2" />
								</dsp:subarg>
							</dsp:novella>
						</dsp:integrazione>
					</modificheattive>
				</disposizioni>
			</meta>
			<intestazione>
				<emanante>Regione Toscana</emanante>
				<tipoDoc>Legge Regionale</tipoDoc>
				<dataDoc norm="20061218">18 dicembre 2006</dataDoc>
				, n.
				<numDoc>62</numDoc>
				<titoloDoc>
					Modifiche alla
					<rif xlink:href="urn:nir:regione.toscana:legge:2004-05-31;28" xlink:type="simple">legge regionale 31 maggio 2004, n. 28</rif>
					(Disciplina delle attività di estetica e di tatuaggio e piercing).
				</titoloDoc>
			</intestazione>
			<formulainiziale>
				<h:p>Il Consiglio Regionale ha approvato il 13.12.2006</h:p>
				<h:p>Il Presidente della Giunta Regionale promulga</h:p>
				<h:p>la seguente legge regionale:</h:p>
			</formulainiziale>
			<articolato>
				<articolo id="art1">
					<num>ARTICOLO 1</num>
					<rubrica>
						(Modifiche all'
						<rif xlink:href="urn:nir:regione.toscana:legge:2004;28#art10" xlink:type="simple">articolo 10 della l.r. 28/2004</rif>
						)
					</rubrica>
					<comma id="art1-com1">
						<num>1.</num>
						<corpo>
							<mod id="mod1">
								Nel
								<rif xlink:href="urn:nir:regione.toscana:legge:2004-05-31;28#art10-com1" xlink:type="simple">comma 1 dell'articolo 10 della legge regionale 31 maggio 2004, n. 28</rif>
								(Disciplina delle attività di estetica e di tatuaggio e piercing), sono soppresse le parole "
								<virgolette id="mod1-vir1" tipo="parola">anche in qualità di lavoratori dipendenti</virgolette>
								".
							</mod>
						</corpo>
					</comma>
					<comma id="art1-com2">
						<num>2.</num>
						<corpo>
							<mod id="mod2">
								Dopo il
								<rif xlink:href="urn:nir:regione.toscana:legge:2004;28#art10-com1" xlink:type="simple">comma 1 dell'articolo 10 della l.r. 28/2004</rif>
								è aggiunto il seguente comma 1 bis: "
								<virgolette id="mod2-vir1" tipo="struttura">
									<comma id="mod2-vir1-com1bis">
										<num>1 bis.</num>
										<corpo>Per coloro che esercitano attività di estetica come lavoratori autonomi ovvero in forma imprenditoriale, il regolamento regionale di cui all'articolo 5 disciplina un percorso ulteriore rispetto a chi esercita l'attività come lavoratore dipendente.</corpo>
									</comma>
								</virgolette>
								".
							</mod>
						</corpo>
					</comma>
					<comma id="art1-com3">
						<num>3.</num>
						<corpo>
							<mmod id="mmo1">
								<mod id="mod3">
									Nei commi
									<rif xlink:href="urn:nir:regione.toscana:legge:2004-05-31;28#art10-com3" xlink:type="simple">3</rif>
								</mod>
								<mod id="mod4">
									e
									<rif xlink:href="urn:nir:regione.toscana:legge:2004;28#art10-com4" xlink:type="simple">4</rif>
									dell'articolo 10 della l.r. 28/2004 le parole "
									<virgolette id="mod4-vir1" tipo="parola">operatore di tatuaggio o piercing</virgolette>
									" sono sostituite da "
									<virgolette id="mod4-vir2" tipo="parola">tecnico qualificato in piercing o tatuaggio</virgolette>
									".
								</mod>
							</mmod>
						</corpo>
					</comma>
					<comma id="art1-com4">
						<num>4.</num>
						<corpo>
							<mod id="mod5">
								Dopo il
								<rif xlink:href="urn:nir:regione.toscana:legge:2004;28#art10-com5" xlink:type="simple">comma 5 dell'articolo 10 della l.r. 28/2004</rif>
								è aggiunto il seguente comma 5 bis: "
								<virgolette id="mod5-vir1" tipo="struttura">
									<comma id="mod5-vir1-com5bis">
										<num>5 bis.</num>
										<corpo>La qualifica di estetista rilasciata ai sensi della presente legge assicura i livelli minimi uniformi di preparazione stabiliti dalle leggi statali.</corpo>
									</comma>
								</virgolette>
								".
							</mod>
						</corpo>
					</comma>
				</articolo>
				<articolo id="art2">
					<num>ARTICOLO 2</num>
					<rubrica>(Applicabilità delle norme)</rubrica>
					<comma id="art2-com1">
						<num>1.</num>
						<corpo>
							Alle disposizioni di cui alla presente legge si applica il differimento dell'efficacia previsto dall'
							<rif xlink:href="urn:nir:regione.toscana:legge:2004;28#art15" xlink:type="simple">articolo 15 della l.r. 28/2004</rif>
							.
						</corpo>
					</comma>
				</articolo>
			</articolato>
			<formulafinale>La presente legge è pubblicata sul Bollettino Ufficiale della Regione. È fatto obbligo a chiunque spetti di osservarla e farla osservare come legge della Regione Toscana.</formulafinale>
			<conclusione>
				<firma tipo="sottoscrizione">MARTINI</firma>
				<dataeluogo codice="00100" norm="">Firenze, 18 dicembre 2006</dataeluogo>
				<soggetto codice="">La presente legge è stata approvata dal Consiglio Regionale nella seduta del 13.12.2006.</soggetto>
			</conclusione>
		</LeggeRegionale>
	</NIR>
